pdb_numpy/DSSP.py
pdb_numpy/__init__.py
pdb_numpy/_align.so
pdb_numpy/abinitio.py
pdb_numpy/alignement.py
pdb_numpy/analysis.py
pdb_numpy/coor.py
pdb_numpy/geom.py
pdb_numpy/model.py
pdb_numpy/select.py
pdb_numpy/visu.py
pdb_numpy/data/__init__.py
pdb_numpy/data/aa_dict.py
pdb_numpy/data/blosum.py
pdb_numpy/data/blosum62.txt
pdb_numpy/format/__init__.py
pdb_numpy/format/gro.py
pdb_numpy/format/mmcif.py
pdb_numpy/format/pdb.py
pdb_numpy/format/pqr.py
pdb_numpy-0.0.2.dist-info/LICENSE
pdb_numpy-0.0.2.dist-info/METADATA
pdb_numpy-0.0.2.dist-info/WHEEL
pdb_numpy-0.0.2.dist-info/entry_points.txt
pdb_numpy-0.0.2.dist-info/top_level.txt
pdb_numpy-0.0.2.dist-info/RECORD
