Metadata-Version: 2.1
Name: pdb-numpy
Version: 0.0.2
Summary: Pdb_Numpy is a python library allowing simple operations on pdb coor files.
Home-page: https://github.com/samuelmurail/pdb_numpy
Author: Samuel Murail
Author-email: samuel.murail@u-paris.fr
License: GNUv2.0
Keywords: pdb_numpy,Python,PDB,Numpy,Coor,Model
Classifier: Development Status :: 4 - Beta
Classifier: Environment :: Console
Classifier: Intended Audience :: Developers
Classifier: Natural Language :: English
Classifier: License :: OSI Approved :: BSD License
Classifier: Programming Language :: Python :: 3 :: Only
Classifier: Programming Language :: Python :: 3
Classifier: Programming Language :: Python :: 3.7
Classifier: Programming Language :: Python :: 3.8
Classifier: Programming Language :: Python :: 3.9
Classifier: Programming Language :: Python :: 3.10
Classifier: Programming Language :: Python :: Implementation :: CPython
Classifier: Programming Language :: Python :: Implementation :: PyPy
Classifier: Programming Language :: Python
Classifier: Topic :: Software Development
Requires-Python: >=3.7
License-File: LICENSE
Requires-Dist: numpy >=1.2
Requires-Dist: scipy >=1.5
